testspgmiciqdistribution/__init__.py
testspgmiciqdistribution-3.0.6.dist-info/METADATA
testspgmiciqdistribution-3.0.6.dist-info/WHEEL
testspgmiciqdistribution-3.0.6.dist-info/RECORD
