Metadata-Version: 2.1
Name: testspgmiciqdistribution
Version: 3.0.6
Summary: SPGMICIQ is an API Client for the S&P Capital IQ API
Keywords: SPGI,S&P Capital IQ API,S&P Global,CIQ API,CIQ Pro,S&P Market Intelligence
Author: SPGMICIQ
Author-email: gds_python_sdk_support@spglobal.com
Requires-Python: >=3.9.0,<4.0.0
Classifier: Programming Language :: Python :: 3
Classifier: Programming Language :: Python :: 3.9
Classifier: Programming Language :: Python :: 3.10
Classifier: Programming Language :: Python :: 3.11
Classifier: Programming Language :: Python :: 3.12
Requires-Dist: IPython (>=8.0,<9.0)
Requires-Dist: Jinja2 (>=3.1.5,<4.0.0)
Requires-Dist: pandas (>=1.1.5)
Requires-Dist: requests (>=2.0,<3.0)
